setup.cfg
setup.py
rotlibrary/rotlibrary.py
rotlibrary.egg-info/PKG-INFO
rotlibrary.egg-info/SOURCES.txt
rotlibrary.egg-info/dependency_links.txt
rotlibrary.egg-info/top_level.txt