Metadata-Version: 2.1
Name: rotlibrary
Version: 1.0
Summary: Library for encypt and decrypt with rot algorithm
Home-page: UNKNOWN
Author-email: pavliknekit6@gmail.com
License: UNKNOWN
Platform: UNKNOWN
